<?xml version="1.0" encoding="UTF-8"?>
<!-- Generated with glade 3.18.3 -->
<interface>
  <requires lib="gtk+" version="3.12"/>
  <object class="GtkWindow" id="window">
    <property name="can_focus">False</property>
    <property name="default_width">800</property>
    <property name="default_height">600</property>
    <child>
      <object class="GtkBox" id="box_img">
        <property name="visible">True</property>
        <property name="can_focus">False</property>
        <child>
          <object class="GtkBox" id="box1">
            <property name="visible">True</property>
            <property name="can_focus">False</property>
            <property name="orientation">vertical</property>
            <child>
              <object class="GtkButtonBox" id="buttonbox">
                <property name="visible">True</property>
                <property name="can_focus">False</property>
                <property name="layout_style">start</property>
                <child>
                  <object class="GtkLabel" id="label7">
                    <property name="visible">True</property>
                    <property name="can_focus">False</property>
                    <property name="label" translatable="yes">Planner</property>
                  </object>
                  <packing>
                    <property name="expand">True</property>
                    <property name="fill">True</property>
                    <property name="position">0</property>
                  </packing>
                </child>
                <child>
                  <object class="GtkButton" id="button_update_costmap">
                    <property name="label" translatable="yes">Update costmap</property>
                    <property name="visible">True</property>
                    <property name="can_focus">True</property>
                    <property name="receives_default">True</property>
                  </object>
                  <packing>
                    <property name="expand">True</property>
                    <property name="fill">True</property>
                    <property name="position">1</property>
                  </packing>
                </child>
                <child>
                  <object class="GtkButton" id="button_run">
                    <property name="label" translatable="yes">Run</property>
                    <property name="visible">True</property>
                    <property name="can_focus">True</property>
                    <property name="receives_default">True</property>
                  </object>
                  <packing>
                    <property name="expand">True</property>
                    <property name="fill">True</property>
                    <property name="position">2</property>
                  </packing>
                </child>
                <child>
                  <object class="GtkButton" id="button_save_path">
                    <property name="label" translatable="yes">Save path</property>
                    <property name="visible">True</property>
                    <property name="can_focus">True</property>
                    <property name="receives_default">True</property>
                    <property name="yalign">0.54000002145767212</property>
                  </object>
                  <packing>
                    <property name="expand">True</property>
                    <property name="fill">True</property>
                    <property name="position">3</property>
                  </packing>
                </child>
                <child>
                  <object class="GtkButton" id="button_load_path">
                    <property name="label" translatable="yes">Load path</property>
                    <property name="visible">True</property>
                    <property name="can_focus">True</property>
                    <property name="receives_default">True</property>
                  </object>
                  <packing>
                    <property name="expand">True</property>
                    <property name="fill">True</property>
                    <property name="position">4</property>
                  </packing>
                </child>
              </object>
              <packing>
                <property name="expand">False</property>
                <property name="fill">True</property>
                <property name="position">0</property>
              </packing>
            </child>
            <child>
              <object class="GtkGrid" id="grid1">
                <property name="visible">True</property>
                <property name="can_focus">False</property>
                <child>
                  <object class="GtkLabel" id="label1">
                    <property name="visible">True</property>
                    <property name="can_focus">False</property>
                    <property name="label" translatable="yes">Start</property>
                  </object>
                  <packing>
                    <property name="left_attach">0</property>
                    <property name="top_attach">1</property>
                  </packing>
                </child>
                <child>
                  <object class="GtkEntry" id="entry_start_x">
                    <property name="visible">True</property>
                    <property name="can_focus">True</property>
                  </object>
                  <packing>
                    <property name="left_attach">1</property>
                    <property name="top_attach">1</property>
                  </packing>
                </child>
                <child>
                  <object class="GtkEntry" id="entry_start_y">
                    <property name="visible">True</property>
                    <property name="can_focus">True</property>
                  </object>
                  <packing>
                    <property name="left_attach">2</property>
                    <property name="top_attach">1</property>
                  </packing>
                </child>
                <child>
                  <object class="GtkEntry" id="entry_start_yaw">
                    <property name="visible">True</property>
                    <property name="can_focus">True</property>
                  </object>
                  <packing>
                    <property name="left_attach">3</property>
                    <property name="top_attach">1</property>
                  </packing>
                </child>
                <child>
                  <object class="GtkLabel" id="label2">
                    <property name="visible">True</property>
                    <property name="can_focus">False</property>
                    <property name="label" translatable="yes">Goal</property>
                  </object>
                  <packing>
                    <property name="left_attach">0</property>
                    <property name="top_attach">2</property>
                  </packing>
                </child>
                <child>
                  <object class="GtkEntry" id="entry_goal_x">
                    <property name="visible">True</property>
                    <property name="can_focus">True</property>
                  </object>
                  <packing>
                    <property name="left_attach">1</property>
                    <property name="top_attach">2</property>
                  </packing>
                </child>
                <child>
                  <object class="GtkEntry" id="entry_goal_y">
                    <property name="visible">True</property>
                    <property name="can_focus">True</property>
                  </object>
                  <packing>
                    <property name="left_attach">2</property>
                    <property name="top_attach">2</property>
                  </packing>
                </child>
                <child>
                  <object class="GtkEntry" id="entry_goal_yaw">
                    <property name="visible">True</property>
                    <property name="can_focus">True</property>
                  </object>
                  <packing>
                    <property name="left_attach">3</property>
                    <property name="top_attach">2</property>
                  </packing>
                </child>
                <child>
                  <object class="GtkLabel" id="label3">
                    <property name="visible">True</property>
                    <property name="can_focus">False</property>
                    <property name="label" translatable="yes">X</property>
                  </object>
                  <packing>
                    <property name="left_attach">1</property>
                    <property name="top_attach">0</property>
                  </packing>
                </child>
                <child>
                  <object class="GtkLabel" id="label4">
                    <property name="visible">True</property>
                    <property name="can_focus">False</property>
                    <property name="label" translatable="yes">Y</property>
                  </object>
                  <packing>
                    <property name="left_attach">2</property>
                    <property name="top_attach">0</property>
                  </packing>
                </child>
                <child>
                  <object class="GtkLabel" id="label5">
                    <property name="visible">True</property>
                    <property name="can_focus">False</property>
                    <property name="label" translatable="yes">Yaw</property>
                  </object>
                  <packing>
                    <property name="left_attach">3</property>
                    <property name="top_attach">0</property>
                  </packing>
                </child>
                <child>
                  <object class="GtkLabel" id="label6">
                    <property name="visible">True</property>
                    <property name="can_focus">False</property>
                    <property name="label" translatable="yes">ROS navgoal</property>
                  </object>
                  <packing>
                    <property name="left_attach">4</property>
                    <property name="top_attach">0</property>
                  </packing>
                </child>
                <child>
                  <object class="GtkToggleButton" id="togglebutton_rec_start">
                    <property name="label" translatable="yes">Record</property>
                    <property name="visible">True</property>
                    <property name="can_focus">True</property>
                    <property name="receives_default">True</property>
                    <property name="xalign">0.49000000953674316</property>
                  </object>
                  <packing>
                    <property name="left_attach">4</property>
                    <property name="top_attach">1</property>
                  </packing>
                </child>
                <child>
                  <object class="GtkToggleButton" id="togglebutton_rec_goal">
                    <property name="label" translatable="yes">Record</property>
                    <property name="visible">True</property>
                    <property name="can_focus">True</property>
                    <property name="receives_default">True</property>
                  </object>
                  <packing>
                    <property name="left_attach">4</property>
                    <property name="top_attach">2</property>
                  </packing>
                </child>
                <child>
                  <placeholder/>
                </child>
              </object>
              <packing>
                <property name="expand">False</property>
                <property name="fill">True</property>
                <property name="position">1</property>
              </packing>
            </child>
          </object>
          <packing>
            <property name="expand">True</property>
            <property name="fill">True</property>
            <property name="position">0</property>
          </packing>
        </child>
        <child>
          <object class="GtkGrid" id="grid_params">
            <property name="visible">True</property>
            <property name="can_focus">False</property>
            <child>
              <placeholder/>
            </child>
            <child>
              <placeholder/>
            </child>
            <child>
              <placeholder/>
            </child>
            <child>
              <placeholder/>
            </child>
            <child>
              <placeholder/>
            </child>
            <child>
              <placeholder/>
            </child>
            <child>
              <placeholder/>
            </child>
            <child>
              <placeholder/>
            </child>
            <child>
              <placeholder/>
            </child>
          </object>
          <packing>
            <property name="expand">False</property>
            <property name="fill">True</property>
            <property name="position">1</property>
          </packing>
        </child>
      </object>
    </child>
  </object>
</interface>
